odoo8_addon_crm_rma_claim_make_claim-8.0.1.0.1-nspkg.pth
odoo_addons/crm_rma_claim_make_claim/README.rst
odoo_addons/crm_rma_claim_make_claim/__init__.py
odoo_addons/crm_rma_claim_make_claim/__openerp__.py
odoo_addons/crm_rma_claim_make_claim/i18n/bg.po
odoo_addons/crm_rma_claim_make_claim/i18n/ca.po
odoo_addons/crm_rma_claim_make_claim/i18n/crm_rma_claim_make_claim.pot
odoo_addons/crm_rma_claim_make_claim/i18n/de.po
odoo_addons/crm_rma_claim_make_claim/i18n/es.po
odoo_addons/crm_rma_claim_make_claim/i18n/es_MX.po
odoo_addons/crm_rma_claim_make_claim/i18n/es_PA.po
odoo_addons/crm_rma_claim_make_claim/i18n/es_VE.po
odoo_addons/crm_rma_claim_make_claim/i18n/eu.po
odoo_addons/crm_rma_claim_make_claim/i18n/fi.po
odoo_addons/crm_rma_claim_make_claim/i18n/fr.po
odoo_addons/crm_rma_claim_make_claim/i18n/it.po
odoo_addons/crm_rma_claim_make_claim/i18n/nb.po
odoo_addons/crm_rma_claim_make_claim/i18n/pt_BR.po
odoo_addons/crm_rma_claim_make_claim/i18n/pt_PT.po
odoo_addons/crm_rma_claim_make_claim/i18n/sk.po
odoo_addons/crm_rma_claim_make_claim/i18n/sl.po
odoo_addons/crm_rma_claim_make_claim/i18n/sv.po
odoo_addons/crm_rma_claim_make_claim/i18n/tr_TR.po
odoo_addons/crm_rma_claim_make_claim/models/__init__.py
odoo_addons/crm_rma_claim_make_claim/models/claim_line.py
odoo_addons/crm_rma_claim_make_claim/models/crm_claim.py
odoo_addons/crm_rma_claim_make_claim/static/description/icon.png
odoo_addons/crm_rma_claim_make_claim/tests/__init__.py
odoo_addons/crm_rma_claim_make_claim/tests/test_crm_rma_claim_make_claim.py
odoo_addons/crm_rma_claim_make_claim/views/claim_line.xml
odoo_addons/crm_rma_claim_make_claim/views/crm_claim.xml
odoo8_addon_crm_rma_claim_make_claim-8.0.1.0.1.dist-info/METADATA
odoo8_addon_crm_rma_claim_make_claim-8.0.1.0.1.dist-info/WHEEL
odoo8_addon_crm_rma_claim_make_claim-8.0.1.0.1.dist-info/namespace_packages.txt
odoo8_addon_crm_rma_claim_make_claim-8.0.1.0.1.dist-info/top_level.txt
odoo8_addon_crm_rma_claim_make_claim-8.0.1.0.1.dist-info/RECORD
